op_opsdevnz/__init__.py
op_opsdevnz/__main__.py
op_opsdevnz/env.py
op_opsdevnz/octodns_hooks.py
op_opsdevnz/onepassword.py
op_opsdevnz/onepassword_sdk.py
op_opsdevnz-0.1.4.dist-info/licenses/LICENSE
opsdevnz/__init__.py
opsdevnz/__main__.py
opsdevnz/env.py
opsdevnz/octodns_hooks.py
opsdevnz/onepassword.py
opsdevnz/onepassword_sdk.py
op_opsdevnz-0.1.4.dist-info/METADATA
op_opsdevnz-0.1.4.dist-info/WHEEL
op_opsdevnz-0.1.4.dist-info/entry_points.txt
op_opsdevnz-0.1.4.dist-info/top_level.txt
op_opsdevnz-0.1.4.dist-info/RECORD
