Metadata-Version: 2.4
Name: op-opsdevnz
Version: 0.1.4
Summary: OpsDev.nz helpers for resolving 1Password secrets with Service Account + CLI fallback.
Author-email: "OpsDev.nz Platform Engineering" <john@opsdev.nz>
Maintainer-email: "OpsDev.nz Platform Engineering" <john@opsdev.nz>
License-Expression: Apache-2.0
Project-URL: Homepage, https://github.com/startmeup-nz/op-opsdevnz
Project-URL: Source, https://github.com/startmeup-nz/op-opsdevnz
Project-URL: Issues, https://github.com/startmeup-nz/op-opsdevnz/issues
Keywords: 1password,secrets,octodns,opsdevnz
Classifier: Development Status :: 3 - Alpha
Classifier: Intended Audience :: Developers
Classifier: Programming Language :: Python
Classifier: Programming Language :: Python :: 3
Classifier: Programming Language :: Python :: 3.9
Classifier: Programming Language :: Python :: 3.10
Classifier: Programming Language :: Python :: 3.11
Classifier: Programming Language :: Python :: 3.12
Classifier: Programming Language :: Python :: 3.13
Classifier: Operating System :: OS Independent
Classifier: Topic :: Security
Classifier: Topic :: System :: Systems Administration
Requires-Python: >=3.9
License-File: LICENSE
Requires-Dist: onepassword-sdk>=0.3.1
Requires-Dist: python-dotenv>=1.0.0
Provides-Extra: dev
Requires-Dist: build>=1.2.2; extra == "dev"
Requires-Dist: mypy>=1.12.0; extra == "dev"
Requires-Dist: pytest>=8.3.0; extra == "dev"
Requires-Dist: pytest-cov>=5.0.0; extra == "dev"
Requires-Dist: pytest-mock>=3.14.0; extra == "dev"
Requires-Dist: ruff>=0.6.5; extra == "dev"
Requires-Dist: twine>=5.1.1; extra == "dev"
Provides-Extra: test
Requires-Dist: pytest>=8.3.0; extra == "test"
Requires-Dist: pytest-mock>=3.14.0; extra == "test"
Dynamic: license-file
